tests/__init__.py
tests/profile_GraphAll.py
tests/test_FDDExceptions.py
tests/test_GraphAll.py
tests/test_ddvav.py
tests/test_helpers.py
tests/test_parser.py
trendreview/FDDExceptions.py
trendreview/GraphAll.py
trendreview/__init__.py
trendreview/__main__.py
trendreview/ddvav.py
trendreview/helpers.py
trendreview/reporting.py
trendreview/sdvav.py
trendreview/trendreview.py
trendreview-0.0.4.dist-info/LICENSE
trendreview-0.0.4.dist-info/METADATA
trendreview-0.0.4.dist-info/WHEEL
trendreview-0.0.4.dist-info/top_level.txt
trendreview-0.0.4.dist-info/RECORD
