Metadata-Version: 2.1
Name: trendreview
Version: 0.0.4
Summary: Reviewed trended data in .csv file format
Home-page: https://github.com/johnvorsten/trendreview
Author: John Vorsten
Author-email: vorstenjohn@gmail.com
License: UNKNOWN
Project-URL: Bug Tracker, https://github.com/johnvorsten/trendreview/issues
Platform: UNKNOWN
Classifier: Programming Language :: Python :: 3
Classifier: License :: OSI Approved :: Mozilla Public License 2.0 (MPL 2.0)
License-File: LICENSE
